supolo/__init__.py
supolo-1.2.2.dist-info/LICENSE
supolo-1.2.2.dist-info/METADATA
supolo-1.2.2.dist-info/WHEEL
supolo-1.2.2.dist-info/top_level.txt
supolo-1.2.2.dist-info/RECORD
