Metadata-Version: 2.1
Name: supolo
Version: 1.2.2
Summary: A fast discord nuke bot based package
Home-page: https://github.com/efenatuyo/supolo
Author: Xolo
License-File: LICENSE
Requires-Dist: aiohttp
